ksphinx/__init__.py
ksphinx/__pkginfo__.py
ksphinx/themes/ksphinx/theme.toml
ksphinx/themes/ksphinx/static/build-info.js
ksphinx/themes/ksphinx/static/highlight.min.js
ksphinx/themes/ksphinx/static/ksphinx.css
ksphinx/themes/ksphinx/static/ksphinx.js
ksphinx/themes/ksphinx/static/fira_codes/ttf/FiraCode-Bold.ttf
ksphinx/themes/ksphinx/static/fira_codes/ttf/FiraCode-Light.ttf
ksphinx/themes/ksphinx/static/fira_codes/ttf/FiraCode-Medium.ttf
ksphinx/themes/ksphinx/static/fira_codes/ttf/FiraCode-Regular.ttf
ksphinx/themes/ksphinx/static/fira_codes/ttf/FiraCode-Retina.ttf
ksphinx/themes/ksphinx/static/fira_codes/ttf/FiraCode-SemiBold.ttf
ksphinx/themes/ksphinx/static/fira_codes/variable_ttf/FiraCode-VF.ttf
ksphinx/themes/ksphinx/static/fira_codes/woff/FiraCode-Bold.woff
ksphinx/themes/ksphinx/static/fira_codes/woff/FiraCode-Light.woff
ksphinx/themes/ksphinx/static/fira_codes/woff/FiraCode-Medium.woff
ksphinx/themes/ksphinx/static/fira_codes/woff/FiraCode-Regular.woff
ksphinx/themes/ksphinx/static/fira_codes/woff/FiraCode-SemiBold.woff
ksphinx/themes/ksphinx/static/fira_codes/woff/FiraCode-VF.woff
ksphinx/themes/ksphinx/static/fira_codes/woff2/FiraCode-Bold.woff2
ksphinx/themes/ksphinx/static/fira_codes/woff2/FiraCode-Light.woff2
ksphinx/themes/ksphinx/static/fira_codes/woff2/FiraCode-Medium.woff2
ksphinx/themes/ksphinx/static/fira_codes/woff2/FiraCode-Regular.woff2
ksphinx/themes/ksphinx/static/fira_codes/woff2/FiraCode-SemiBold.woff2
ksphinx/themes/ksphinx/static/fira_codes/woff2/FiraCode-VF.woff2
ksphinx/themes/ksphinx/static/fontello/fontello.eot
ksphinx/themes/ksphinx/static/fontello/fontello.svg
ksphinx/themes/ksphinx/static/fontello/fontello.ttf
ksphinx/themes/ksphinx/static/fontello/fontello.woff
ksphinx/themes/ksphinx/static/fontello/fontello.woff2
ksphinx/themes/ksphinx/templates/build-info.html
ksphinx/themes/ksphinx/templates/layout.html
ksphinx/themes/ksphinx/templates/localtoc.html
ksphinx/themes/ksphinx/templates/relations.html
ksphinx-0.2.0.dist-info/licenses/LICENSE
ksphinx-0.2.0.dist-info/METADATA
ksphinx-0.2.0.dist-info/WHEEL
ksphinx-0.2.0.dist-info/entry_points.txt
ksphinx-0.2.0.dist-info/top_level.txt
ksphinx-0.2.0.dist-info/RECORD
